poca/__init__.py
poca/about.py
poca/args.py
poca/config.py
poca/entryinfo.py
poca/feedstats.py
poca/files.py
poca/history.py
poca/loggers.py
poca/lxmlfuncs.py
poca/outcome.py
poca/output.py
poca/subscribe.py
poca/subupdate.py
poca/subupgrade.py
poca/tag.py
poca/xmlconf.py
poca-1.1.data/data/share/man/man1/poca-subscribe.1
poca-1.1.data/data/share/man/man1/poca.1
poca-1.1.data/scripts/poca
poca-1.1.data/scripts/poca-subscribe
poca-1.1.dist-info/LICENSE.txt
poca-1.1.dist-info/METADATA
poca-1.1.dist-info/WHEEL
poca-1.1.dist-info/top_level.txt
poca-1.1.dist-info/RECORD
