Metadata-Version: 2.1
Name: poca
Version: 1.1
Summary: A fast and customizable command line podcast client
Home-page: https://github.com/brokkr/poca
Author: Mads Michelsen
Author-email: mail@brokkr.net
License: GPL3
Keywords: podcast,client,aggregator,cli
Platform: POSIX
Classifier: Development Status :: 5 - Production/Stable
Classifier: Environment :: Console
Classifier: Intended Audience :: End Users/Desktop
Classifier: License :: OSI Approved :: GNU General Public License (GPL)
Classifier: Natural Language :: English
Classifier: Operating System :: POSIX
Classifier: Programming Language :: Python :: 3.6
Classifier: Topic :: Multimedia :: Sound/Audio
Requires: feedparser
Requires: lxml
Requires: mutagen
Requires: requests
Provides: poca
License-File: LICENSE.txt
Requires-Dist: feedparser
Requires-Dist: lxml
Requires-Dist: mutagen
Requires-Dist: requests
